nr/__init__.py
nr/parsing/__init__.py
nr/parsing/core/__init__.py
nr/parsing/core/py.typed
nr/parsing/core/rules.py
nr/parsing/core/scanner.py
nr/parsing/core/tokenizer/__init__.py
nr/parsing/core/tokenizer/extractor.py
nr/parsing/core/tokenizer/ruleset.py
nr/parsing/core/tokenizer/tokenizer.py
nr.parsing.core-2.0.4.dist-info/LICENSE.txt
nr.parsing.core-2.0.4.dist-info/METADATA
nr.parsing.core-2.0.4.dist-info/WHEEL
nr.parsing.core-2.0.4.dist-info/top_level.txt
nr.parsing.core-2.0.4.dist-info/RECORD
