Metadata-Version: 2.1
Name: nr.parsing.core
Version: 2.0.4
Summary: A simple API to scan and tokenize text for the purpose of structured language processing.
Home-page: https://git.niklasrosenstein.com/NiklasRosenstein/nr
Author: Niklas Rosenstein
Author-email: rosensteinniklas@gmail.com
License: MIT
Platform: UNKNOWN
Requires-Python: >=3.6.0,<4.0.0
